{
  "femaleNames": [
    { "name": "Adina" },
    { "name": "Akala" },
    { "name": "Akuna" },
    { "name": "Alinta" },
    { "name": "Alira" },
    { "name": "Alkawari" },
    { "name": "Alkina" },
    { "name": "Allira" },
    { "name": "Angoona" },
    { "name": "Anmanari" },
    { "name": "Bindi" },
    { "name": "Biralee" },
    { "name": "Brindabella" },
    { "name": "Cardinia" },
    { "name": "Darana" },
    { "name": "Elanora" },
    { "name": "Ellin" },
    { "name": "Iluka" },
    { "name": "Inala" },
    { "name": "Inyuwa" },
    { "name": "Jannali" },
    { "name": "Jedda" },
    { "name": "Jiemba" },
    { "name": "Jindalee" },
    { "name": "Kaawa" },
    { "name": "Karalee" },
    { "name": "Kareela" },
    { "name": "Karri" },
    { "name": "Kiah" },
    { "name": "Kirra" },
    { "name": "Kyeema" },
    { "name": "Lenah" },
    { "name": "Leumeah" },
    { "name": "Lowanna" },
    { "name": "Lutana" },
    { "name": "Makinti" },
    { "name": "Maroochy" },
    { "name": "Merinda" },
    { "name": "Merindah" },
    { "name": "Merri" },
    { "name": "Mokee" },
    { "name": "Myaree" },
    { "name": "Naata" },
    { "name": "Ngoia" },
    { "name": "Nioka" },
    { "name": "Nymbulda" },
    { "name": "Nyurapayia" },
    { "name": "Oola" },
    { "name": "Papalya" },
    { "name": "Parara" },
    { "name": "Payu" },
    { "name": "Pengana" },
    { "name": "Pirrmangka" },
    { "name": "Tahlee" },
    { "name": "Takariya" },
    { "name": "Talilia" },
    { "name": "Tallara" },
    { "name": "Tamminya" },
    { "name": "Tanganutura" },
    { "name": "Tarni" },
    { "name": "Tatali" },
    { "name": "Tharah" },
    { "name": "Tidam" },
    { "name": "Tjunkiya" },
    { "name": "Truganina" },
    { "name": "Truganini" },
    { "name": "Trugernanner" },
    { "name": "Walangkura" },
    { "name": "Waratah" },
    { "name": "Wintjiya" },
    { "name": "Yakari" },
    { "name": "Yalamay" },
    { "name": "Yinarupa" },
    { "name": "Yindi" },
    { "name": "Olivia" },
    { "name": "Mia" },
    { "name": "Charlotte" },
    { "name": "Amelia" },
    { "name": "Ava" },
    { "name": "Emily" },
    { "name": "Chloe" },
    { "name": "Ruby" },
    { "name": "Isabella" },
    { "name": "Sophie" },
    { "name": "Grace" },
    { "name": "Ella" },
    { "name": "Isla" },
    { "name": "Sophia" },
    { "name": "Zoe" },
    { "name": "Sienna" },
    { "name": "Ivy" },
    { "name": "Evie" },
    { "name": "Scarlett" },
    { "name": "Emma" },
    { "name": "Lily" },
    { "name": "Matilda" },
    { "name": "Hannah" },
    { "name": "Harper" },
    { "name": "Zara" },
    { "name": "Georgia" },
    { "name": "Lucy" },
    { "name": "Layla" },
    { "name": "Abigail" },
    { "name": "Annabelle" },
    { "name": "Evelyn" },
    { "name": "Eva" },
    { "name": "Isabelle" },
    { "name": "Jasmine" },
    { "name": "Willow" },
    { "name": "Audrey" },
    { "name": "Sofia" },
    { "name": "Maddison" },
    { "name": "Imogen" },
    { "name": "Jessica" },
    { "name": "Aria" },
    { "name": "Mila" },
    { "name": "Maya" },
    { "name": "Sarah" },
    { "name": "Savannah" },
    { "name": "Alexis" },
    { "name": "Alice" },
    { "name": "Stella" },
    { "name": "Violet" },
    { "name": "Elizabeth" },
    { "name": "Poppy" },
    { "name": "Ellie" },
    { "name": "Chelsea" },
    { "name": "Summer" },
    { "name": "Anna" },
    { "name": "Bella" },
    { "name": "Claire" },
    { "name": "Madison" },
    { "name": "Victoria" },
    { "name": "Phoebe" },
    { "name": "Eloise" },
    { "name": "Lola" },
    { "name": "Piper" },
    { "name": "Addison" },
    { "name": "Indiana" },
    { "name": "Alyssa" },
    { "name": "Holly" },
    { "name": "Lilly" },
    { "name": "Eden" },
    { "name": "Lara" },
    { "name": "Madeleine" },
    { "name": "Ariana" },
    { "name": "Rose" },
    { "name": "Aaliyah" },
    { "name": "Paige" },
    { "name": "Isabel" },
    { "name": "Lillian" },
    { "name": "Alexandra" },
    { "name": "Hayley" },
    { "name": "Elise" },
    { "name": "Emilia" },
    { "name": "Eleanor" },
    { "name": "Eliza" },
    { "name": "Molly" },
    { "name": "Olive" },
    { "name": "Lexi" },
    { "name": "Madeline" },
    { "name": "Penelope" },
    { "name": "Hazel" },
    { "name": "Amelie" },
    { "name": "Harriet" },
    { "name": "Mackenzie" },
    { "name": "Elsie" },
    { "name": "Jade" },
    { "name": "Natalie" },
    { "name": "Ayla" },
    { "name": "Charlie" },
    { "name": "Indie" },
    { "name": "Frankie" },
    { "name": "Samantha" }
  ],
  "maleNames": [
    { "name": "Anatjari" },
    { "name": "Bambam" },
    { "name": "Beangagarrie" },
    { "name": "Colebee" },
    { "name": "Daku" },
    { "name": "Darana" },
    { "name": "Djalu" },
    { "name": "Dural" },
    { "name": "Gurumarra" },
    { "name": "Iluka" },
    { "name": "Jabo" },
    { "name": "Jarli" },
    { "name": "Jarrah" },
    { "name": "Jiemba" },
    { "name": "Kaawa" },
    { "name": "Kuparr" },
    { "name": "Mangana" },
    { "name": "Mokee" },
    { "name": "Nicermenic" },
    { "name": "Nyakul" },
    { "name": "Nyukuti" },
    { "name": "Omeo" },
    { "name": "Tidam" },
    { "name": "Toba" },
    { "name": "Waku" },
    { "name": "Waratah" },
    { "name": "Warragul" },
    { "name": "Warrin" },
    { "name": "Yannathan" },
    { "name": "Yarramundi" },
    { "name": "Yarran" },
    { "name": "Oliver" },
    { "name": "William" },
    { "name": "Noah" },
    { "name": "Jack" },
    { "name": "James" },
    { "name": "Lucas" },
    { "name": "Thomas" },
    { "name": "Alexander" },
    { "name": "Ethan" },
    { "name": "Liam" },
    { "name": "Max" },
    { "name": "Jacob" },
    { "name": "Cooper" },
    { "name": "Isaac" },
    { "name": "Lachlan" },
    { "name": "Harrison" },
    { "name": "Joshua" },
    { "name": "Samuel" },
    { "name": "Benjamin" },
    { "name": "Mason" },
    { "name": "Henry" },
    { "name": "Charlie" },
    { "name": "Ryan" },
    { "name": "Daniel" },
    { "name": "Jayden" },
    { "name": "Oscar" },
    { "name": "Harry" },
    { "name": "Hunter" },
    { "name": "Leo" },
    { "name": "Xavier" },
    { "name": "Elijah" },
    { "name": "Sebastian" },
    { "name": "Archie" },
    { "name": "George" },
    { "name": "Jackson" },
    { "name": "Levi" },
    { "name": "Logan" },
    { "name": "Aiden" },
    { "name": "Nicholas" },
    { "name": "Flynn" },
    { "name": "Riley" },
    { "name": "Hugo" },
    { "name": "Matthew" },
    { "name": "Tyler" },
    { "name": "Hudson" },
    { "name": "Adam" },
    { "name": "Edward" },
    { "name": "Michael" },
    { "name": "Zachary" },
    { "name": "Joseph" },
    { "name": "Patrick" },
    { "name": "Dylan" },
    { "name": "Nate" },
    { "name": "Jake" },
    { "name": "Jaxon" },
    { "name": "Luke" },
    { "name": "Kai" },
    { "name": "Luca" },
    { "name": "Archer" },
    { "name": "Ashton" },
    { "name": "Beau" },
    { "name": "Jordan" },
    { "name": "Eli" },
    { "name": "Connor" },
    { "name": "Marcus" },
    { "name": "Ali" },
    { "name": "Austin" },
    { "name": "Finn" },
    { "name": "Gabriel" },
    { "name": "Lincoln" },
    { "name": "Christian" },
    { "name": "Jasper" },
    { "name": "Nathan" },
    { "name": "Blake" },
    { "name": "Chase" },
    { "name": "Braxton" },
    { "name": "Louis" },
    { "name": "Angus" },
    { "name": "Dominic" },
    { "name": "Muhammad" },
    { "name": "Toby" },
    { "name": "Hayden" },
    { "name": "Caleb" },
    { "name": "Bailey" },
    { "name": "Hamish" },
    { "name": "Felix" },
    { "name": "Anthony" },
    { "name": "Charles" },
    { "name": "Owen" },
    { "name": "Aaron" },
    { "name": "Ryder" },
    { "name": "David" },
    { "name": "John" },
    { "name": "Christopher" },
    { "name": "Jesse" },
    { "name": "Phoenix" },
    { "name": "Darcy" },
    { "name": "Jonathan" },
    { "name": "Maxwell" },
    { "name": "Omar" }
  ],
  "surnames": [
    {
      "name": "Smith",
      "weight": 18.0
    },
    {
      "name": "Jones",
      "weight": 10.0
    },
    {
      "name": "Brown",
      "weight": 9.0
    },
    {
      "name": "Williams",
      "weight": 9.0
    },
    {
      "name": "Wilson",
      "weight": 8.0
    },
    {
      "name": "Taylor",
      "weight": 8.0
    },
    {
      "name": "Lee",
      "weight": 6.0
    },
    {
      "name": "Johnson",
      "weight": 5.0
    },
    {
      "name": "Anderson",
      "weight": 5.0
    },
    {
      "name": "White",
      "weight": 5.0
    },
    {
      "name": "Thompson",
      "weight": 5.0
    },
    {
      "name": "Martin",
      "weight": 5.0
    },
    {
      "name": "Thomas",
      "weight": 5.0
    },
    {
      "name": "Walker",
      "weight": 5.0
    },
    {
      "name": "Harris",
      "weight": 4.0
    },
    {
      "name": "King",
      "weight": 4.0
    },
    {
      "name": "Kelly",
      "weight": 4.0
    },
    {
      "name": "Ryan",
      "weight": 4.0
    },
    {
      "name": "Campbell",
      "weight": 4.0
    },
    {
      "name": "Evans",
      "weight": 4.0
    },
    {
      "name": "Roberts",
      "weight": 4.0
    },
    {
      "name": "Young",
      "weight": 4.0
    },
    {
      "name": "Hall",
      "weight": 4.0
    },
    {
      "name": "Robinson",
      "weight": 4.0
    },
    {
      "name": "Davis",
      "weight": 4.0
    },
    {
      "name": "Edwards",
      "weight": 4.0
    },
    {
      "name": "Wright",
      "weight": 4.0
    },
    {
      "name": "Clark",
      "weight": 4.0
    },
    {
      "name": "Clarke",
      "weight": 4.0
    },
    {
      "name": "Green",
      "weight": 4.0
    },
    {
      "name": "Baker",
      "weight": 4.0
    },
    {
      "name": "Moore",
      "weight": 4.0
    },
    {
      "name": "Scott",
      "weight": 4.0
    },
    {
      "name": "Turner",
      "weight": 4.0
    },
    {
      "name": "Hill",
      "weight": 4.0
    },
    {
      "name": "Miller",
      "weight": 4.0
    },
    {
      "name": "Mitchell",
      "weight": 4.0
    },
    {
      "name": "Nguyen",
      "weight": 4.0
    },
    {
      "name": "Stewart",
      "weight": 4.0
    },
    {
      "name": "McDonald",
      "weight": 4.0
    },
    {
      "name": "Watson",
      "weight": 4.0
    },
    {
      "name": "Jackson",
      "weight": 3.0
    },
    {
      "name": "Cooper",
      "weight": 3.0
    },
    {
      "name": "James",
      "weight": 3.0
    },
    {
      "name": "Murphy",
      "weight": 3.0
    },
    {
      "name": "Bell",
      "weight": 3.0
    },
    {
      "name": "Wood",
      "weight": 3.0
    },
    {
      "name": "Lewis",
      "weight": 3.0
    },
    {
      "name": "Collins",
      "weight": 3.0
    },
    {
      "name": "Singh",
      "weight": 3.0
    },
    {
      "name": "Allen",
      "weight": 3.0
    },
    {
      "name": "Murray",
      "weight": 3.0
    },
    {
      "name": "Cook",
      "weight": 3.0
    },
    {
      "name": "Hughes",
      "weight": 3.0
    },
    {
      "name": "Morris",
      "weight": 3.0
    },
    {
      "name": "Phillips",
      "weight": 3.0
    },
    {
      "name": "Davies",
      "weight": 3.0
    },
    {
      "name": "Ward",
      "weight": 3.0
    },
    {
      "name": "Johnston",
      "weight": 3.0
    },
    {
      "name": "Bennett",
      "weight": 3.0
    },
    {
      "name": "Robertson",
      "weight": 3.0
    },
    {
      "name": "Gray",
      "weight": 3.0
    },
    {
      "name": "Parker",
      "weight": 3.0
    },
    {
      "name": "O'Brien",
      "weight": 3.0
    },
    {
      "name": "Morgan",
      "weight": 3.0
    },
    {
      "name": "Graham",
      "weight": 3.0
    },
    {
      "name": "Adams",
      "weight": 3.0
    },
    {
      "name": "Russell",
      "weight": 3.0
    },
    {
      "name": "Ross",
      "weight": 3.0
    },
    {
      "name": "Harrison",
      "weight": 3.0
    },
    {
      "name": "Carter",
      "weight": 3.0
    },
    {
      "name": "Kennedy",
      "weight": 3.0
    },
    {
      "name": "Simpson",
      "weight": 3.0
    },
    {
      "name": "Marshall",
      "weight": 3.0
    },
    {
      "name": "Reid",
      "weight": 3.0
    },
    {
      "name": "Richardson",
      "weight": 2.0
    },
    {
      "name": "Richards",
      "weight": 2.0
    },
    {
      "name": "Cox",
      "weight": 2.0
    },
    {
      "name": "Walsh",
      "weight": 2.0
    },
    {
      "name": "Bailey",
      "weight": 2.0
    },
    {
      "name": "Rogers",
      "weight": 2.0
    },
    {
      "name": "Wang",
      "weight": 2.0
    },
    {
      "name": "Chen",
      "weight": 2.0
    },
    {
      "name": "Li",
      "weight": 2.0
    },
    {
      "name": "Cameron",
      "weight": 2.0
    },
    {
      "name": "Stevens",
      "weight": 2.0
    },
    {
      "name": "Chapman",
      "weight": 2.0
    },
    {
      "name": "Wong",
      "weight": 2.0
    },
    {
      "name": "Webb",
      "weight": 2.0
    },
    {
      "name": "Harvey",
      "weight": 2.0
    },
    {
      "name": "Matthews",
      "weight": 2.0
    },
    {
      "name": "Grant",
      "weight": 2.0
    },
    {
      "name": "Shaw",
      "weight": 2.0
    },
    {
      "name": "Thomson",
      "weight": 2.0
    },
    {
      "name": "Tran",
      "weight": 2.0
    },
    {
      "name": "Fisher",
      "weight": 2.0
    },
    {
      "name": "Butler",
      "weight": 2.0
    },
    {
      "name": "Mills",
      "weight": 2.0
    },
    {
      "name": "Hamilton",
      "weight": 2.0
    },
    {
      "name": "Hunt",
      "weight": 2.0
    },
    {
      "name": "Ellis",
      "weight": 2.0
    },
    {
      "name": "Price",
      "weight": 2.0
    },
    {
      "name": "Mason",
      "weight": 2.0
    },
    {
      "name": "Fraser",
      "weight": 2.0
    },
    {
      "name": "Armstrong",
      "weight": 2.0
    },
    {
      "name": "Henderson",
      "weight": 2.0
    },
    {
      "name": "McKenzie",
      "weight": 2.0
    },
    {
      "name": "Knight",
      "weight": 2.0
    },
    {
      "name": "Pearce",
      "weight": 2.0
    },
    {
      "name": "Barnes",
      "weight": 2.0
    },
    {
      "name": "Zhang",
      "weight": 2.0
    },
    {
      "name": "Howard",
      "weight": 2.0
    },
    {
      "name": "Ferguson",
      "weight": 2.0
    },
    {
      "name": "Hunter",
      "weight": 2.0
    },
    {
      "name": "Elliott",
      "weight": 2.0
    },
    {
      "name": "Hayes",
      "weight": 2.0
    },
    {
      "name": "Dunn",
      "weight": 2.0
    },
    {
      "name": "Gibson",
      "weight": 2.0
    },
    {
      "name": "Ford",
      "weight": 2.0
    },
    {
      "name": "Chan",
      "weight": 2.0
    },
    {
      "name": "Wallace",
      "weight": 2.0
    },
    {
      "name": "Foster",
      "weight": 2.0
    },
    {
      "name": "Andrews",
      "weight": 2.0
    },
    {
      "name": "Gordon",
      "weight": 2.0
    },
    {
      "name": "Palmer",
      "weight": 2.0
    },
    {
      "name": "Burns",
      "weight": 2.0
    },
    {
      "name": "Sullivan",
      "weight": 2.0
    },
    {
      "name": "Griffiths",
      "weight": 2.0
    },
    {
      "name": "Woods",
      "weight": 2.0
    },
    {
      "name": "Holmes",
      "weight": 2.0
    },
    {
      "name": "West",
      "weight": 2.0
    },
    {
      "name": "Black",
      "weight": 2.0
    },
    {
      "name": "Tan",
      "weight": 2.0
    },
    {
      "name": "McLean",
      "weight": 2.0
    },
    {
      "name": "Rose",
      "weight": 2.0
    },
    {
      "name": "Reynolds",
      "weight": 2.0
    },
    {
      "name": "Dawson",
      "weight": 2.0
    },
    {
      "name": "Day",
      "weight": 2.0
    },
    {
      "name": "Jenkins",
      "weight": 2.0
    },
    {
      "name": "Morrison",
      "weight": 2.0
    },
    {
      "name": "Byrne",
      "weight": 2.0
    },
    {
      "name": "Saunders",
      "weight": 2.0
    },
    {
      "name": "Liu",
      "weight": 2.0
    },
    {
      "name": "Powell",
      "weight": 2.0
    },
    {
      "name": "Dixon",
      "weight": 2.0
    },
    {
      "name": "FitzGerald",
      "weight": 2.0
    },
    {
      "name": "Davidson",
      "weight": 2.0
    },
    {
      "name": "O'Connor",
      "weight": 2.0
    },
    {
      "name": "Patel",
      "weight": 2.0
    },
    {
      "name": "Fletcher",
      "weight": 1.0
    },
    {
      "name": "Watts",
      "weight": 1.0
    },
    {
      "name": "Macdonald",
      "weight": 1.0
    },
    {
      "name": "Barker",
      "weight": 1.0
    },
    {
      "name": "Wilkinson",
      "weight": 1.0
    },
    {
      "name": "Kerr",
      "weight": 1.0
    },
    {
      "name": "Carroll",
      "weight": 1.0
    },
    {
      "name": "Perry",
      "weight": 1.0
    },
    {
      "name": "Kim",
      "weight": 1.0
    },
    {
      "name": "Payne",
      "weight": 1.0
    },
    {
      "name": "Doyle",
      "weight": 1.0
    },
    {
      "name": "Lawrence",
      "weight": 1.0
    },
    {
      "name": "Cole",
      "weight": 1.0
    },
    {
      "name": "Hart",
      "weight": 1.0
    },
    {
      "name": "Duncan",
      "weight": 1.0
    },
    {
      "name": "Williamson",
      "weight": 1.0
    },
    {
      "name": "McCarthy",
      "weight": 1.0
    },
    {
      "name": "Brooks",
      "weight": 1.0
    },
    {
      "name": "Lynch",
      "weight": 1.0
    },
    {
      "name": "Lim",
      "weight": 1.0
    },
    {
      "name": "Rowe",
      "weight": 1.0
    },
    {
      "name": "Nelson",
      "weight": 1.0
    },
    {
      "name": "Lane",
      "weight": 1.0
    },
    {
      "name": "Wells",
      "weight": 1.0
    },
    {
      "name": "Francis",
      "weight": 1.0
    },
    {
      "name": "Stone",
      "weight": 1.0
    },
    {
      "name": "Lloyd",
      "weight": 1.0
    },
    {
      "name": "Fox",
      "weight": 1.0
    },
    {
      "name": "Stephens",
      "weight": 1.0
    },
    {
      "name": "Porter",
      "weight": 1.0
    },
    {
      "name": "Peters",
      "weight": 1.0
    },
    {
      "name": "Newman",
      "weight": 1.0
    },
    {
      "name": "George",
      "weight": 1.0
    },
    {
      "name": "Pearson",
      "weight": 1.0
    },
    {
      "name": "Spencer",
      "weight": 1.0
    },
    {
      "name": "Webster",
      "weight": 1.0
    },
    {
      "name": "Douglas",
      "weight": 1.0
    },
    {
      "name": "Alexander",
      "weight": 1.0
    },
    {
      "name": "Lowe",
      "weight": 1.0
    },
    {
      "name": "Gill",
      "weight": 1.0
    },
    {
      "name": "O'Neill",
      "weight": 1.0
    },
    {
      "name": "Crawford",
      "weight": 1.0
    },
    {
      "name": "Freeman",
      "weight": 1.0
    },
    {
      "name": "Boyd",
      "weight": 1.0
    },
    {
      "name": "Coleman",
      "weight": 1.0
    },
    {
      "name": "May",
      "weight": 1.0
    },
    {
      "name": "Burgess",
      "weight": 1.0
    },
    {
      "name": "Dean",
      "weight": 1.0
    },
    {
      "name": "Burke",
      "weight": 1.0
    },
    {
      "name": "McMahon",
      "weight": 1.0
    },
    {
      "name": "Barrett",
      "weight": 1.0
    }
  ]
}
